iptracker/__init__.py
iptracker-1.0.4.dist-info/LICENSE
iptracker-1.0.4.dist-info/METADATA
iptracker-1.0.4.dist-info/WHEEL
iptracker-1.0.4.dist-info/top_level.txt
iptracker-1.0.4.dist-info/RECORD
