Metadata-Version: 2.2
Name: iptracker
Version: 1.0.4
Summary: A Python package for tracking IP addresses and their locations.
Home-page: https://github.com/ishanoshada/iptracker
Author: Ishan Oshada
Author-email: ishan.kodithuwakku.official@email.com
Classifier: Programming Language :: Python :: 3
Classifier: License :: OSI Approved :: MIT License
Classifier: Operating System :: OS Independent
License-File: LICENSE
Requires-Dist: requests
Dynamic: author
Dynamic: author-email
Dynamic: classifier
Dynamic: description
Dynamic: description-content-type
Dynamic: home-page
Dynamic: requires-dist
Dynamic: summary
